xenaPython/__init__.py
xenaPython/convert.py
xenaPython/example.py
xenaPython/jupyter.js
xenaPython/jupyter.py
xenaPython/startxena.sh
xenaPython/xenaAPI.py
xenaPython/xenaQuery.py
xenaPython/queries/allCohorts.xq
xenaPython/queries/allDatasets.xq
xenaPython/queries/allDatasetsN.xq
xenaPython/queries/allFieldMetadata.xq
xenaPython/queries/cohortSamples.xq
xenaPython/queries/cohortSummary.xq
xenaPython/queries/datasetFetch.xq
xenaPython/queries/datasetField.xq
xenaPython/queries/datasetFieldExamples.xq
xenaPython/queries/datasetFieldN.xq
xenaPython/queries/datasetGeneProbeAvg.xq
xenaPython/queries/datasetGeneProbesValues.xq
xenaPython/queries/datasetList.xq
xenaPython/queries/datasetMetadata.xq
xenaPython/queries/datasetProbeSignature.xq
xenaPython/queries/datasetProbeValues.xq
xenaPython/queries/datasetSamples.xq
xenaPython/queries/datasetSamplesNDenseMatrix.xq
xenaPython/queries/datasetSources.xq
xenaPython/queries/datasetStatus.xq
xenaPython/queries/datasetsNullRows.xq
xenaPython/queries/featureList.xq
xenaPython/queries/fieldCodes.xq
xenaPython/queries/fieldMetadata.xq
xenaPython/queries/geneTranscripts.xq
xenaPython/queries/matchFields.xq
xenaPython/queries/probeCount.xq
xenaPython/queries/probemapList.xq
xenaPython/queries/refGeneExons.xq
xenaPython/queries/refGenePosition.xq
xenaPython/queries/refGeneRange.xq
xenaPython/queries/segmentDataExamples.xq
xenaPython/queries/segmentedDataRange.xq
xenaPython/queries/sparseData.xq
xenaPython/queries/sparseDataExamples.xq
xenaPython/queries/sparseDataMatchField.xq
xenaPython/queries/sparseDataMatchFieldSlow.xq
xenaPython/queries/sparseDataMatchPartialField.xq
xenaPython/queries/sparseDataRange.xq
xenaPython/queries/transcriptExpression.xq
xenaPython-1.0.14.dist-info/LICENSE
xenaPython-1.0.14.dist-info/METADATA
xenaPython-1.0.14.dist-info/WHEEL
xenaPython-1.0.14.dist-info/top_level.txt
xenaPython-1.0.14.dist-info/RECORD
